{
  "nodes": [
    {
      "id": "a37a8b83",
      "type": "objectStore",
      "x": 420,
      "y": 300,
      "name": "Upload Bucket",
      "publicPermissions": "write",
      "wires": [
        [
          "cbfe948a"
        ]
      ]
    },
    {
      "id": "cbfe948a",
      "type": "function",
      "x": 620,
      "y": 400,
      "name": "Trigger",
      "runtime": "nodejs",
      "envVars": {
        "DESTINATION_BUCKET": "${node.Destination_Bucket.id}"
      },
      "wires": [
        [
          "22059371"
        ]
      ]
    },
    {
      "id": "1cb6725b",
      "type": "objectStore",
      "x": 1530,
      "y": 400,
      "name": "Destination Bucket",
      "wires": [
        []
      ]
    },
    {
      "id": "87e8e5c4",
      "type": "virtualNetwork",
      "x": 1040,
      "y": 460,
      "width": 600,
      "height": 400
    },
    {
      "id": "fce7b7b1",
      "type": "dockerCluster",
      "x": 960,
      "y": 400,
      "width": 240,
      "height": 160,
      "instanceType": "t2.micro",
      "minInstances": 1,
      "maxInstances": 1,
      "computeScaleIn": 0.3,
      "computeScaleOut": 0.7,
      "memoryScaleIn": 0.3,
      "memoryScaleOut": 0.7,
      "scalePercentage": 0.1
    },
    {
      "id": "22059371",
      "type": "dockerService",
      "x": 940,
      "y": 400,
      "containers": [
        {
          "image": "quay.io/txase/imageconverter",
          "computeUnits": 256,
          "memory": 256
        }
      ],
      "minInstances": 0,
      "maxInstances": 0,
      "computeScaleIn": 0.3,
      "computeScaleOut": 0.7,
      "scalePercentage": 0.1,
      "envVars": {}
    }
  ]
}